odoo/addons/l10n_br_cte/README.rst
odoo/addons/l10n_br_cte/__init__.py
odoo/addons/l10n_br_cte/__manifest__.py
odoo/addons/l10n_br_cte/hooks.py
odoo/addons/l10n_br_cte/constants/cte.py
odoo/addons/l10n_br_cte/constants/modal.py
odoo/addons/l10n_br_cte/data/ir_config_parameter.xml
odoo/addons/l10n_br_cte/demo/company_demo.xml
odoo/addons/l10n_br_cte/demo/fiscal_document_demo.xml
odoo/addons/l10n_br_cte/i18n/l10n_br_cte.pot
odoo/addons/l10n_br_cte/i18n/pt_BR.po
odoo/addons/l10n_br_cte/models/__init__.py
odoo/addons/l10n_br_cte/models/aereo.py
odoo/addons/l10n_br_cte/models/aquaviario.py
odoo/addons/l10n_br_cte/models/document.py
odoo/addons/l10n_br_cte/models/document_cargo_quantity_infos.py
odoo/addons/l10n_br_cte/models/document_comment.py
odoo/addons/l10n_br_cte/models/document_line.py
odoo/addons/l10n_br_cte/models/document_mixin.py
odoo/addons/l10n_br_cte/models/document_related.py
odoo/addons/l10n_br_cte/models/document_supplement.py
odoo/addons/l10n_br_cte/models/document_transported_vehicles.py
odoo/addons/l10n_br_cte/models/document_type.py
odoo/addons/l10n_br_cte/models/dutoviario.py
odoo/addons/l10n_br_cte/models/ferroviario.py
odoo/addons/l10n_br_cte/models/res_city.py
odoo/addons/l10n_br_cte/models/res_company.py
odoo/addons/l10n_br_cte/models/res_config_settings.py
odoo/addons/l10n_br_cte/models/res_country.py
odoo/addons/l10n_br_cte/models/res_country_state.py
odoo/addons/l10n_br_cte/models/res_partner.py
odoo/addons/l10n_br_cte/models/rodoviario.py
odoo/addons/l10n_br_cte/readme/CONFIGURE.md
odoo/addons/l10n_br_cte/readme/CONTRIBUTORS.md
odoo/addons/l10n_br_cte/readme/DESCRIPTION.md
odoo/addons/l10n_br_cte/readme/ROADMAP.md
odoo/addons/l10n_br_cte/readme/USAGE.md
odoo/addons/l10n_br_cte/report/__init__.py
odoo/addons/l10n_br_cte/report/dacte_report.xml
odoo/addons/l10n_br_cte/report/ir_actions_report.py
odoo/addons/l10n_br_cte/security/ir.model.access.csv
odoo/addons/l10n_br_cte/static/description/icon.png
odoo_addon_l10n_br_cte-16.0.9.0.0.dist-info/METADATA
odoo_addon_l10n_br_cte-16.0.9.0.0.dist-info/WHEEL
odoo_addon_l10n_br_cte-16.0.9.0.0.dist-info/top_level.txt
odoo_addon_l10n_br_cte-16.0.9.0.0.dist-info/RECORD
